{"nodes": [{"name": "First World Congress Happenings", "type": "event", "year": "1965", "id": 0, "x": 100, "y": 100}, {"name": "Octopus Allstars", "type": "person", "id": 1, "x": 100, "y": 100}, {"name": "Al Hansen", "type": "person", "id": 2, "x": 100, "y": 100}, {"name": "Eric Andersen", "type": "person", "id": 3, "x": 100, "y": 100}, {"name": "George Brecht", "type": "person", "id": 4, "x": 100, "y": 100}, {"name": "Christo", "type": "person", "id": 5, "x": 100, "y": 100}, {"name": "Robert Filliou", "type": "person", "id": 6, "x": 100, "y": 100}, {"name": "Dick Higgins", "type": "person", "id": 7, "x": 100, "y": 100}, {"name": "Ray Johnson", "type": "person", "id": 8, "x": 100, "y": 100}, {"name": "Alison Knowles", "type": "person", "id": 9, "x": 100, "y": 100}, {"name": "Jackson Mac Low", "type": "person", "id": 10, "x": 100, "y": 100}, {"name": "Yoko Ono", "type": "person", "id": 11, "x": 100, "y": 100}, {"name": "Nam-june Paik", "type": "person", "id": 12, "x": 100, "y": 100}, {"name": "Ben Patterson", "type": "person", "id": 13, "x": 100, "y": 100}, {"name": "Tomas Schmit", "type": "person", "id": 14, "x": 100, "y": 100}, {"name": "Wolf Vostell", "type": "person", "id": 15, "x": 100, "y": 100}, {"name": "La Monte Young", "type": "person", "id": 16, "x": 100, "y": 100}], "edges": [{"source": 1, "target": 0, "value": 1}, {"source": 2, "target": 0, "value": 1}, {"source": 3, "target": 0, "value": 1}, {"source": 4, "target": 0, "value": 1}, {"source": 5, "target": 0, "value": 1}, {"source": 6, "target": 0, "value": 1}, {"source": 2, "target": 0, "value": 1}, {"source": 7, "target": 0, "value": 1}, {"source": 8, "target": 0, "value": 1}, {"source": 9, "target": 0, "value": 1}, {"source": 10, "target": 0, "value": 1}, {"source": 11, "target": 0, "value": 1}, {"source": 12, "target": 0, "value": 1}, {"source": 13, "target": 0, "value": 1}, {"source": 14, "target": 0, "value": 1}, {"source": 15, "target": 0, "value": 1}, {"source": 16, "target": 0, "value": 1}]}