{"nodes": [{"name": "Yoko Ono", "id": "2", "url": "yoko ono", "authority": "Yoko Ono", "counter": 0, "hasEdge": true}, {"name": "Walter De Maria", "id": "27", "url": "walter de maria", "authority": "Walter De Maria", "counter": 1, "hasEdge": true}, {"name": "Jackson Mac Low", "id": "28", "url": "jackson mac low", "authority": "Jackson Mac Low", "counter": 2, "hasEdge": true}, {"name": "Robert Watts", "id": "30", "url": "robert watts", "authority": "Robert Watts (artist)", "counter": 3, "hasEdge": true}, {"name": "Ben Patterson", "id": "34", "url": "ben patterson", "authority": "Ben Patterson", "counter": 4, "hasEdge": true}, {"name": "Ay-O", "id": "88", "url": "ay o", "authority": "Ay-O", "counter": 5, "hasEdge": true}, {"name": "Takehisa Kosugi", "id": "96", "url": "takehisa kosugi", "authority": "Takehisa Kosugi", "counter": 6, "hasEdge": true}, {"name": "Hi Red Center", "id": "146", "url": "hi red center", "authority": "http://padb.net/resource/Hi Red Center", "counter": 7, "hasEdge": true}, {"name": "Joe Jones", "id": "186", "url": "joe jones", "authority": "Joe Jones (Fluxus artist)", "counter": 8, "hasEdge": true}, {"name": "Shigeko Kubota", "id": "262", "url": "shigeko kubota", "authority": "Shigeko Kubota", "counter": 9, "hasEdge": true}, {"name": "Anthony Cox", "id": "319", "url": "anthony cox", "authority": "Anthony Cox (producer)", "counter": 10, "hasEdge": true}, {"name": "Glue Mamma", "id": "351", "url": "glue mamma", "authority": "http://padb.net/resource/Glue Mamma", "counter": 11, "hasEdge": true}], "edges": [{"sourceName": "yoko ono", "targetName": "walter de maria", "source": 0, "target": 1, "sourceDbId": "2", "targetDbId": "27", "dates": ["1965-09-05"], "cities": ["new york city", "New York City"], "countries": ["united states", "United States"]}, {"sourceName": "yoko ono", "targetName": "jackson mac low", "source": 0, "target": 2, "sourceDbId": "2", "targetDbId": "28", "dates": ["1965-09-05"], "cities": ["new york city", "New York City"], "countries": ["united states", "United States"]}, {"sourceName": "yoko ono", "targetName": "robert watts", "source": 0, "target": 3, "sourceDbId": "2", "targetDbId": "30", "dates": ["1965-09-05"], "cities": ["new york city", "New York City"], "countries": ["united states", "United States"]}, {"sourceName": "yoko ono", "targetName": "ben patterson", "source": 0, "target": 4, "sourceDbId": "2", "targetDbId": "34", "dates": ["1965-09-05"], "cities": ["new york city", "New York City"], "countries": ["united states", "United States"]}, {"sourceName": "yoko ono", "targetName": "ay o", "source": 0, "target": 5, "sourceDbId": "2", "targetDbId": "88", "dates": ["1965-09-05"], "cities": ["new york city", "New York City"], "countries": ["united states", "United States"]}, {"sourceName": "yoko ono", "targetName": "takehisa kosugi", "source": 0, "target": 6, "sourceDbId": "2", "targetDbId": "96", "dates": ["1965-09-05"], "cities": ["new york city", "New York City"], "countries": ["united states", "United States"]}, {"sourceName": "yoko ono", "targetName": "hi red center", "source": 0, "target": 7, "sourceDbId": "2", "targetDbId": "146", "dates": ["1965-09-05"], "cities": ["new york city", "New York City"], "countries": ["united states", "United States"]}, {"sourceName": "yoko ono", "targetName": "joe jones", "source": 0, "target": 8, "sourceDbId": "2", "targetDbId": "186", "dates": ["1965-09-05"], "cities": ["new york city", "New York City"], "countries": ["united states", "United States"]}, {"sourceName": "yoko ono", "targetName": "shigeko kubota", "source": 0, "target": 9, "sourceDbId": "2", "targetDbId": "262", "dates": ["1965-09-05"], "cities": ["new york city", "New York City"], "countries": ["united states", "United States"]}, {"sourceName": "yoko ono", "targetName": "anthony cox", "source": 0, "target": 10, "sourceDbId": "2", "targetDbId": "319", "dates": ["1965-09-05"], "cities": ["new york city", "New York City"], "countries": ["united states", "United States"]}, {"sourceName": "yoko ono", "targetName": "glue mamma", "source": 0, "target": 11, "sourceDbId": "2", "targetDbId": "351", "dates": ["1965-09-05"], "cities": ["new york city", "New York City"], "countries": ["united states", "United States"]}, {"sourceName": "walter de maria", "targetName": "jackson mac low", "source": 1, "target": 2, "sourceDbId": "27", "targetDbId": "28", "dates": ["1965-09-05"], "cities": ["new york city", "New York City"], "countries": ["united states", "United States"]}, {"sourceName": "walter de maria", "targetName": "robert watts", "source": 1, "target": 3, "sourceDbId": "27", "targetDbId": "30", "dates": ["1965-09-05"], "cities": ["new york city", "New York City"], "countries": ["united states", "United States"]}, {"sourceName": "walter de maria", "targetName": "ben patterson", "source": 1, "target": 4, "sourceDbId": "27", "targetDbId": "34", "dates": ["1965-09-05"], "cities": ["new york city", "New York City"], "countries": ["united states", "United States"]}, {"sourceName": "walter de maria", "targetName": "ay o", "source": 1, "target": 5, "sourceDbId": "27", "targetDbId": "88", "dates": ["1965-09-05"], "cities": ["new york city", "New York City"], "countries": ["united states", "United States"]}, {"sourceName": "walter de maria", "targetName": "takehisa kosugi", "source": 1, "target": 6, "sourceDbId": "27", "targetDbId": "96", "dates": ["1965-09-05"], "cities": ["new york city", "New York City"], "countries": ["united states", "United States"]}, {"sourceName": "walter de maria", "targetName": "hi red center", "source": 1, "target": 7, "sourceDbId": "27", "targetDbId": "146", "dates": ["1965-09-05"], "cities": ["new york city", "New York City"], "countries": ["united states", "United States"]}, {"sourceName": "walter de maria", "targetName": "joe jones", "source": 1, "target": 8, "sourceDbId": "27", "targetDbId": "186", "dates": ["1965-09-05"], "cities": ["new york city", "New York City"], "countries": ["united states", "United States"]}, {"sourceName": "walter de maria", "targetName": "shigeko kubota", "source": 1, "target": 9, "sourceDbId": "27", "targetDbId": "262", "dates": ["1965-09-05"], "cities": ["new york city", "New York City"], "countries": ["united states", "United States"]}, {"sourceName": "walter de maria", "targetName": "anthony cox", "source": 1, "target": 10, "sourceDbId": "27", "targetDbId": "319", "dates": ["1965-09-05"], "cities": ["new york city", "New York City"], "countries": ["united states", "United States"]}, {"sourceName": "walter de maria", "targetName": "glue mamma", "source": 1, "target": 11, "sourceDbId": "27", "targetDbId": "351", "dates": ["1965-09-05"], "cities": ["new york city", "New York City"], "countries": ["united states", "United States"]}, {"sourceName": "jackson mac low", "targetName": "robert watts", "source": 2, "target": 3, "sourceDbId": "28", "targetDbId": "30", "dates": ["1965-09-05"], "cities": ["new york city", "New York City"], "countries": ["united states", "United States"]}, {"sourceName": "jackson mac low", "targetName": "ben patterson", "source": 2, "target": 4, "sourceDbId": "28", "targetDbId": "34", "dates": ["1965-09-05"], "cities": ["new york city", "New York City"], "countries": ["united states", "United States"]}, {"sourceName": "jackson mac low", "targetName": "ay o", "source": 2, "target": 5, "sourceDbId": "28", "targetDbId": "88", "dates": ["1965-09-05"], "cities": ["new york city", "New York City"], "countries": ["united states", "United States"]}, {"sourceName": "jackson mac low", "targetName": "takehisa kosugi", "source": 2, "target": 6, "sourceDbId": "28", "targetDbId": "96", "dates": ["1965-09-05"], "cities": ["new york city", "New York City"], "countries": ["united states", "United States"]}, {"sourceName": "jackson mac low", "targetName": "hi red center", "source": 2, "target": 7, "sourceDbId": "28", "targetDbId": "146", "dates": ["1965-09-05"], "cities": ["new york city", "New York City"], "countries": ["united states", "United States"]}, {"sourceName": "jackson mac low", "targetName": "joe jones", "source": 2, "target": 8, "sourceDbId": "28", "targetDbId": "186", "dates": ["1965-09-05"], "cities": ["new york city", "New York City"], "countries": ["united states", "United States"]}, {"sourceName": "jackson mac low", "targetName": "shigeko kubota", "source": 2, "target": 9, "sourceDbId": "28", "targetDbId": "262", "dates": ["1965-09-05"], "cities": ["new york city", "New York City"], "countries": ["united states", "United States"]}, {"sourceName": "jackson mac low", "targetName": "anthony cox", "source": 2, "target": 10, "sourceDbId": "28", "targetDbId": "319", "dates": ["1965-09-05"], "cities": ["new york city", "New York City"], "countries": ["united states", "United States"]}, {"sourceName": "jackson mac low", "targetName": "glue mamma", "source": 2, "target": 11, "sourceDbId": "28", "targetDbId": "351", "dates": ["1965-09-05"], "cities": ["new york city", "New York City"], "countries": ["united states", "United States"]}, {"sourceName": "robert watts", "targetName": "ben patterson", "source": 3, "target": 4, "sourceDbId": "30", "targetDbId": "34", "dates": ["1965-09-05"], "cities": ["new york city", "New York City"], "countries": ["united states", "United States"]}, {"sourceName": "robert watts", "targetName": "ay o", "source": 3, "target": 5, "sourceDbId": "30", "targetDbId": "88", "dates": ["1965-09-05"], "cities": ["new york city", "New York City"], "countries": ["united states", "United States"]}, {"sourceName": "robert watts", "targetName": "takehisa kosugi", "source": 3, "target": 6, "sourceDbId": "30", "targetDbId": "96", "dates": ["1965-09-05"], "cities": ["new york city", "New York City"], "countries": ["united states", "United States"]}, {"sourceName": "robert watts", "targetName": "hi red center", "source": 3, "target": 7, "sourceDbId": "30", "targetDbId": "146", "dates": ["1965-09-05"], "cities": ["new york city", "New York City"], "countries": ["united states", "United States"]}, {"sourceName": "robert watts", "targetName": "joe jones", "source": 3, "target": 8, "sourceDbId": "30", "targetDbId": "186", "dates": ["1965-09-05"], "cities": ["new york city", "New York City"], "countries": ["united states", "United States"]}, {"sourceName": "robert watts", "targetName": "shigeko kubota", "source": 3, "target": 9, "sourceDbId": "30", "targetDbId": "262", "dates": ["1965-09-05"], "cities": ["new york city", "New York City"], "countries": ["united states", "United States"]}, {"sourceName": "robert watts", "targetName": "anthony cox", "source": 3, "target": 10, "sourceDbId": "30", "targetDbId": "319", "dates": ["1965-09-05"], "cities": ["new york city", "New York City"], "countries": ["united states", "United States"]}, {"sourceName": "robert watts", "targetName": "glue mamma", "source": 3, "target": 11, "sourceDbId": "30", "targetDbId": "351", "dates": ["1965-09-05"], "cities": ["new york city", "New York City"], "countries": ["united states", "United States"]}, {"sourceName": "ben patterson", "targetName": "ay o", "source": 4, "target": 5, "sourceDbId": "34", "targetDbId": "88", "dates": ["1965-09-05"], "cities": ["new york city", "New York City"], "countries": ["united states", "United States"]}, {"sourceName": "ben patterson", "targetName": "takehisa kosugi", "source": 4, "target": 6, "sourceDbId": "34", "targetDbId": "96", "dates": ["1965-09-05"], "cities": ["new york city", "New York City"], "countries": ["united states", "United States"]}, {"sourceName": "ben patterson", "targetName": "hi red center", "source": 4, "target": 7, "sourceDbId": "34", "targetDbId": "146", "dates": ["1965-09-05"], "cities": ["new york city", "New York City"], "countries": ["united states", "United States"]}, {"sourceName": "ben patterson", "targetName": "joe jones", "source": 4, "target": 8, "sourceDbId": "34", "targetDbId": "186", "dates": ["1965-09-05"], "cities": ["new york city", "New York City"], "countries": ["united states", "United States"]}, {"sourceName": "ben patterson", "targetName": "shigeko kubota", "source": 4, "target": 9, "sourceDbId": "34", "targetDbId": "262", "dates": ["1965-09-05"], "cities": ["new york city", "New York City"], "countries": ["united states", "United States"]}, {"sourceName": "ben patterson", "targetName": "anthony cox", "source": 4, "target": 10, "sourceDbId": "34", "targetDbId": "319", "dates": ["1965-09-05"], "cities": ["new york city", "New York City"], "countries": ["united states", "United States"]}, {"sourceName": "ben patterson", "targetName": "glue mamma", "source": 4, "target": 11, "sourceDbId": "34", "targetDbId": "351", "dates": ["1965-09-05"], "cities": ["new york city", "New York City"], "countries": ["united states", "United States"]}, {"sourceName": "ay o", "targetName": "takehisa kosugi", "source": 5, "target": 6, "sourceDbId": "88", "targetDbId": "96", "dates": ["1965-09-05"], "cities": ["new york city", "New York City"], "countries": ["united states", "United States"]}, {"sourceName": "ay o", "targetName": "hi red center", "source": 5, "target": 7, "sourceDbId": "88", "targetDbId": "146", "dates": ["1965-09-05"], "cities": ["new york city", "New York City"], "countries": ["united states", "United States"]}, {"sourceName": "ay o", "targetName": "joe jones", "source": 5, "target": 8, "sourceDbId": "88", "targetDbId": "186", "dates": ["1965-09-05"], "cities": ["new york city", "New York City"], "countries": ["united states", "United States"]}, {"sourceName": "ay o", "targetName": "shigeko kubota", "source": 5, "target": 9, "sourceDbId": "88", "targetDbId": "262", "dates": ["1965-09-05"], "cities": ["new york city", "New York City"], "countries": ["united states", "United States"]}, {"sourceName": "ay o", "targetName": "anthony cox", "source": 5, "target": 10, "sourceDbId": "88", "targetDbId": "319", "dates": ["1965-09-05"], "cities": ["new york city", "New York City"], "countries": ["united states", "United States"]}, {"sourceName": "ay o", "targetName": "glue mamma", "source": 5, "target": 11, "sourceDbId": "88", "targetDbId": "351", "dates": ["1965-09-05"], "cities": ["new york city", "New York City"], "countries": ["united states", "United States"]}, {"sourceName": "takehisa kosugi", "targetName": "hi red center", "source": 6, "target": 7, "sourceDbId": "96", "targetDbId": "146", "dates": ["1965-09-05"], "cities": ["new york city", "New York City"], "countries": ["united states", "United States"]}, {"sourceName": "takehisa kosugi", "targetName": "joe jones", "source": 6, "target": 8, "sourceDbId": "96", "targetDbId": "186", "dates": ["1965-09-05"], "cities": ["new york city", "New York City"], "countries": ["united states", "United States"]}, {"sourceName": "takehisa kosugi", "targetName": "shigeko kubota", "source": 6, "target": 9, "sourceDbId": "96", "targetDbId": "262", "dates": ["1965-09-05"], "cities": ["new york city", "New York City"], "countries": ["united states", "United States"]}, {"sourceName": "takehisa kosugi", "targetName": "anthony cox", "source": 6, "target": 10, "sourceDbId": "96", "targetDbId": "319", "dates": ["1965-09-05"], "cities": ["new york city", "New York City"], "countries": ["united states", "United States"]}, {"sourceName": "takehisa kosugi", "targetName": "glue mamma", "source": 6, "target": 11, "sourceDbId": "96", "targetDbId": "351", "dates": ["1965-09-05"], "cities": ["new york city", "New York City"], "countries": ["united states", "United States"]}, {"sourceName": "hi red center", "targetName": "joe jones", "source": 7, "target": 8, "sourceDbId": "146", "targetDbId": "186", "dates": ["1965-09-05"], "cities": ["new york city", "New York City"], "countries": ["united states", "United States"]}, {"sourceName": "hi red center", "targetName": "shigeko kubota", "source": 7, "target": 9, "sourceDbId": "146", "targetDbId": "262", "dates": ["1965-09-05"], "cities": ["new york city", "New York City"], "countries": ["united states", "United States"]}, {"sourceName": "hi red center", "targetName": "anthony cox", "source": 7, "target": 10, "sourceDbId": "146", "targetDbId": "319", "dates": ["1965-09-05"], "cities": ["new york city", "New York City"], "countries": ["united states", "United States"]}, {"sourceName": "hi red center", "targetName": "glue mamma", "source": 7, "target": 11, "sourceDbId": "146", "targetDbId": "351", "dates": ["1965-09-05"], "cities": ["new york city", "New York City"], "countries": ["united states", "United States"]}, {"sourceName": "joe jones", "targetName": "shigeko kubota", "source": 8, "target": 9, "sourceDbId": "186", "targetDbId": "262", "dates": ["1965-09-05"], "cities": ["new york city", "New York City"], "countries": ["united states", "United States"]}, {"sourceName": "joe jones", "targetName": "anthony cox", "source": 8, "target": 10, "sourceDbId": "186", "targetDbId": "319", "dates": ["1965-09-05"], "cities": ["new york city", "New York City"], "countries": ["united states", "United States"]}, {"sourceName": "joe jones", "targetName": "glue mamma", "source": 8, "target": 11, "sourceDbId": "186", "targetDbId": "351", "dates": ["1965-09-05"], "cities": ["new york city", "New York City"], "countries": ["united states", "United States"]}, {"sourceName": "shigeko kubota", "targetName": "anthony cox", "source": 9, "target": 10, "sourceDbId": "262", "targetDbId": "319", "dates": ["1965-09-05"], "cities": ["new york city", "New York City"], "countries": ["united states", "United States"]}, {"sourceName": "shigeko kubota", "targetName": "glue mamma", "source": 9, "target": 11, "sourceDbId": "262", "targetDbId": "351", "dates": ["1965-09-05"], "cities": ["new york city", "New York City"], "countries": ["united states", "United States"]}, {"sourceName": "anthony cox", "targetName": "glue mamma", "source": 10, "target": 11, "sourceDbId": "319", "targetDbId": "351", "dates": ["1965-09-05"], "cities": ["new york city", "New York City"], "countries": ["united states", "United States"]}]}