{"city": "http://dbpedia.org/resource/Venice", "country": "http://dbpedia.org/resource/Italy", "title": "Galleria il Canale", "authority": "", "address": "", "events": [{"date": "1960-06-18", "title": "Anti-Process", "participants": ["Jean-Jacques Lebel", "Sergio Rusconi", "Alain_Jouffroy"], "url": "anti_process_1960_6_18"}], "nodes": [{"name": "Jean-Jacques Lebel", "id": "24", "url": "jean_jacques_lebel", "authority": "http://dbpedia.org/resource/Jean-Jacques_Lebel", "counter": 0}, {"name": "Sergio Rusconi", "id": "37", "url": "sergio_rusconi", "authority": "http://padb.net/resource/Sergio_Rusconi", "counter": 1}, {"name": "Alain_Jouffroy", "id": "38", "url": "alain_jouffroy", "authority": "http://id.loc.gov/authorities/names/n50038815", "counter": 2}], "edges": [{"sourceName": "jean_jacques_lebel", "targetName": "sergio_rusconi", "source": 0, "target": 1, "sourceDbId": "24", "targetDbId": "37", "dates": ["1960-06-18"], "cities": ["http://dbpedia.org/resource/venice", "http://dbpedia.org/resource/Venice"], "countries": ["http://dbpedia.org/resource/italy", "http://dbpedia.org/resource/Italy"]}, {"sourceName": "jean_jacques_lebel", "targetName": "alain_jouffroy", "source": 0, "target": 2, "sourceDbId": "24", "targetDbId": "38", "dates": ["1960-06-18"], "cities": ["http://dbpedia.org/resource/venice", "http://dbpedia.org/resource/Venice"], "countries": ["http://dbpedia.org/resource/italy", "http://dbpedia.org/resource/Italy"]}, {"sourceName": "sergio_rusconi", "targetName": "alain_jouffroy", "source": 1, "target": 2, "sourceDbId": "37", "targetDbId": "38", "dates": ["1960-06-18"], "cities": ["http://dbpedia.org/resource/venice", "http://dbpedia.org/resource/Venice"], "countries": ["http://dbpedia.org/resource/italy", "http://dbpedia.org/resource/Italy"]}]}